aleksis/apps/fritak/README.md
aleksis/apps/fritak/__init__.py
aleksis/apps/fritak/admin.py
aleksis/apps/fritak/apps.py
aleksis/apps/fritak/decorators.py
aleksis/apps/fritak/filters.py
aleksis/apps/fritak/forms.py
aleksis/apps/fritak/frontend/index.js
aleksis/apps/fritak/frontend/messages/de.json
aleksis/apps/fritak/frontend/messages/en.json
aleksis/apps/fritak/frontend/messages/ru.json
aleksis/apps/fritak/frontend/messages/uk.json
aleksis/apps/fritak/locale/ar/LC_MESSAGES/django.mo
aleksis/apps/fritak/locale/ar/LC_MESSAGES/django.po
aleksis/apps/fritak/locale/de_DE/LC_MESSAGES/django.mo
aleksis/apps/fritak/locale/de_DE/LC_MESSAGES/django.po
aleksis/apps/fritak/locale/fr/LC_MESSAGES/django.mo
aleksis/apps/fritak/locale/fr/LC_MESSAGES/django.po
aleksis/apps/fritak/locale/la/LC_MESSAGES/django.mo
aleksis/apps/fritak/locale/la/LC_MESSAGES/django.po
aleksis/apps/fritak/locale/nb_NO/LC_MESSAGES/django.mo
aleksis/apps/fritak/locale/nb_NO/LC_MESSAGES/django.po
aleksis/apps/fritak/locale/ru/LC_MESSAGES/django.mo
aleksis/apps/fritak/locale/ru/LC_MESSAGES/django.po
aleksis/apps/fritak/locale/tr_TR/LC_MESSAGES/django.mo
aleksis/apps/fritak/locale/tr_TR/LC_MESSAGES/django.po
aleksis/apps/fritak/locale/uk/LC_MESSAGES/django.mo
aleksis/apps/fritak/locale/uk/LC_MESSAGES/django.po
aleksis/apps/fritak/migrations/0001_initial.py
aleksis/apps/fritak/migrations/__init__.py
aleksis/apps/fritak/models.py
aleksis/apps/fritak/rules.py
aleksis/apps/fritak/templates/fritak/applied_for.html
aleksis/apps/fritak/templates/fritak/apply_for.html
aleksis/apps/fritak/templates/fritak/archive.html
aleksis/apps/fritak/templates/fritak/archive_print.html
aleksis/apps/fritak/templates/fritak/check.html
aleksis/apps/fritak/templates/fritak/edit.html
aleksis/apps/fritak/templates/fritak/index.html
aleksis/apps/fritak/urls.py
aleksis/apps/fritak/views.py
aleksis_app_fritak-3.0.dist-info/METADATA
aleksis_app_fritak-3.0.dist-info/WHEEL
aleksis_app_fritak-3.0.dist-info/entry_points.txt
aleksis_app_fritak-3.0.dist-info/RECORD
