Metadata-Version: 2.1
Name: aleksis-app-fritak
Version: 3.0
Summary: Unofficial AlekSIS App Fritak (Management of exemption requests)
Home-page: https://edugit.org/katharineum/AlekSIS-App-Fritak
License: EUPL-1.2
Author: Julian Leucker
Author-email: leuckeju@katharineum.de
Maintainer: Frank Poetzsch-Heffter
Maintainer-email: p-h@katharineum.de
Requires-Python: >=3.9,<4.0
Classifier: Development Status :: 5 - Production/Stable
Classifier: Environment :: Web Environment
Classifier: Intended Audience :: Education
Classifier: License :: OSI Approved :: European Union Public Licence 1.2 (EUPL 1.2)
Classifier: Programming Language :: Python :: 3
Classifier: Programming Language :: Python :: 3.9
Classifier: Programming Language :: Python :: 3.10
Classifier: Programming Language :: Python :: 3.11
Classifier: Topic :: Education
Requires-Dist: aleksis-core (>=3.0,<4.0)
Project-URL: Repository, https://edugit.org/katharineum/AlekSIS-App-Fritak
